MANIFEST.in
Makefile
README.md
pyproject.toml
setup.cfg
setup.py
plyflatten/__about__.py
plyflatten/__init__.py
plyflatten/cli.py
plyflatten/rasterization.py
plyflatten/utils.py
plyflatten.egg-info/PKG-INFO
plyflatten.egg-info/SOURCES.txt
plyflatten.egg-info/dependency_links.txt
plyflatten.egg-info/entry_points.txt
plyflatten.egg-info/requires.txt
plyflatten.egg-info/top_level.txt
src/fail.c
src/plyflatten.c
src/xmalloc.c