Metadata-Version: 2.1
Name: plyflatten
Version: 0.2.0
Summary: Take a series of ply files and produce a digital elevation map
Home-page: https://github.com/cmla/plyflatten
Author: Carlo de Franchis
Author-email: carlo.de-franchis@ens-cachan.fr
License: UNKNOWN
Platform: UNKNOWN
Provides-Extra: dev
Provides-Extra: test
